Metadata-Version: 2.1
Name: trading212-api-extended
Version: 1.0.1
Summary: An Extended (unofficial) Rest API client for Trading212
Author-email: Antonio Caserta <a.caserta@proton.me>
License: MIT
Project-URL: homepage, https://github.com/amstrdm/trading212-api-extended
Keywords: trading212,api,client,trading,finance
Requires-Python: >=3.10
License-File: LICENSE
Requires-Dist: requests
